{"name":"Autoin","tagline":"Auto-In plugin for Minecraft servers.","body":"# **TODO**\r\n### Welcome to Auto-In page.\r\nAenean sit amet ex quam. Sed venenatis pulvinar commodo. Donec euismod neque nisl, vel egestas magna lobortis eu. Lorem ipsum dolor sit amet, consectetur adipiscing elit. Ut facilisis consequat posuere. Sed nec felis egestas, lacinia felis ac, condimentum nunc. Suspendisse id risus tristique, aliquet mi a, bibendum nisl. Etiam felis eros, vehicula id purus vel, malesuada semper eros. Vestibulum ante ipsum primis in faucibus orci luctus et ultrices posuere cubilia Curae; Fusce lobortis nibh mi. Fusce ut hendrerit ex. Proin iaculis sodales tortor. Fusce consequat nunc vitae turpis feugiat, ac tincidunt eros vestibulum. Etiam porttitor finibus ultrices. Aliquam ultricies, nulla eu tincidunt placerat, enim dolor posuere tortor, ut eleifend nisl ex vel dolor.\r\n\r\n```\r\n$ sit amet, consectetur adipiscing elit\r\n$ Vestibulum ante ipsum primis in faucibus orci luctus et ultrices posuere cubilia Curae\r\n$ Fusce ut hendrerit ex\r\n```\r\n\r\nNeque porro quisquam est qui dolorem ipsum quia dolor sit amet, consectetur, adipisci velit..\r\n\r\n***\r\n\r\n### Description \r\nVestibulum posuere tortor non libero condimentum tempus. Suspendisse feugiat id felis non consectetur. Mauris vitae ultrices ligula. Ut mattis nisi nunc, eu pellentesque neque eleifend nec. Praesent at interdum lorem. Nam gravida ornare odio non fringilla. Suspendisse sit amet egestas dolor. Suspendisse tristique ultrices ultricies. Nulla facilisi. Nullam et est eu ipsum consectetur bibendum. Vestibulum ante ipsum primis in faucibus orci luctus et ultrices posuere cubilia Curae; Aliquam faucibus rutrum commodo.\r\n> unc ac tellus non risus tempus molestie. Mauris facilisis mattis lacus ut mattis. Integer vulputate leo eu eros elementum, at venenatis enim molestie. Nam eleifend justo purus, at tempor augue fringilla a. Integer tempus ante ut pulvinar aliquet. Nunc quis cursus quam. Quisque enim nibh, semper vitae bibendum eget, convallis vel libero. Sed eu turpis venenatis, interdum eros eu, tristique magna.\r\n\r\n### Support or Contact\r\nAliquam erat volutpat. Cras blandit faucibus ligula et mattis. Sed sodales mi id turpis lacinia egestas. Nunc non nisi nulla. Vestibulum id nisl viverra, semper sapien sed, vestibulum est. Etiam ornare urna maximus nisl pulvinar, in dictum ligula porttitor. Duis feugiat ex in metus sodales lacinia. Praesent maximus massa dui, non ultrices est interdum vitae. In tristique vel risus ac dictum. ","google":"","note":"Don't delete this file! It's used internally to help with page regeneration."}